setup.py
django_searchify.egg-info/PKG-INFO
django_searchify.egg-info/SOURCES.txt
django_searchify.egg-info/dependency_links.txt
django_searchify.egg-info/requires.txt
django_searchify.egg-info/top_level.txt
searchify/__init__.py
searchify/hooks.py
searchify/index.py
searchify/models.py
searchify/search.py
searchify/utils.py
searchify/clients/__init__.py
searchify/clients/pyes_client.py
searchify/clients/restpose_client.py
searchify/clients/unconfigured_client.py
searchify/management/__init__.py
searchify/management/commands/__init__.py
searchify/management/commands/searchify_reindex.py
searchify/management/commands/searchify_show.py