Metadata-Version: 1.1
Name: django-searchify
Version: 0.4
Summary: Search integration for Django with a focus on indexing
Home-page: UNKNOWN
Author: James Aylett
Author-email: james@tartarus.org
License: MIT
Platform: UNKNOWN
Classifier: Intended Audience :: Developers
Classifier: Framework :: Django
Classifier: License :: OSI Approved :: MIT License
Classifier: Programming Language :: Python :: 2
Classifier: Topic :: Internet :: WWW/HTTP :: Indexing/Search
